message.py
prompt.py
record.py
synapse.py
topic.py
python_echo-0.1.0.dist-info/licenses/LICENSE
python_echo-0.1.0.dist-info/METADATA
python_echo-0.1.0.dist-info/WHEEL
python_echo-0.1.0.dist-info/top_level.txt
python_echo-0.1.0.dist-info/RECORD
