Metadata-Version: 2.4
Name: python-echo
Version: 0.1.0
Summary: Echo is a lightweight and intuitive Python library for building and managing LLM-based chat conversations.
Author-email: Omer Menashe <unspecified@mail.com>
License-Expression: MIT
Project-URL: Source, https://github.com/iamomerm/python-echo
Keywords: python-echo,echo
Classifier: Programming Language :: Python :: 3
Classifier: Operating System :: OS Independent
Requires-Python: >=3.7
License-File: LICENSE
Dynamic: license-file
